osucore-0.1.11.dist-info/METADATA
osucore-0.1.11.dist-info/WHEEL
osucore/__init__.py
osucore/osucore.cpython-38-x86_64-linux-gnu.so
osucore-0.1.11.dist-info/RECORD
